ketils/__init__.py
ketils/ketils.py
ketils/utils.py
ketils-0.0.0.dist-info/LICENSE
ketils-0.0.0.dist-info/METADATA
ketils-0.0.0.dist-info/WHEEL
ketils-0.0.0.dist-info/top_level.txt
ketils-0.0.0.dist-info/RECORD
