Metadata-Version: 2.1
Name: ketils
Version: 0.0.0
Summary: A python package that provides several utilities related to KEGG.
Author: Innocent Labs
Author-email: jakec63738@gmail.com
License: MIT
Requires-Python: >=3.9.0
License-File: LICENSE
